krishnautoml/__init__.py
krishnautoml/automl.py
krishnautoml/cli.py
krishnautoml/data/__init__.py
krishnautoml/data/feature_engineering.py
krishnautoml/data/loader.py
krishnautoml/data/preprocessing.py
krishnautoml/eda/__init__.py
krishnautoml/eda/eda_report.py
krishnautoml/evaluation/__init__.py
krishnautoml/evaluation/evaluator.py
krishnautoml/models/__init__.py
krishnautoml/models/base_model.py
krishnautoml/models/catboost_model.py
krishnautoml/models/lightgbm_model.py
krishnautoml/models/model_factory.py
krishnautoml/models/xgboost_model.py
krishnautoml/reporting/__init__.py
krishnautoml/reporting/report_generator.py
krishnautoml/reporting/templates/report_template.html
krishnautoml/tuning/__init__.py
krishnautoml/tuning/tuner.py
krishnautoml/utils/__init__.py
krishnautoml/utils/helpers.py
krishnautoml-1.0.8.dist-info/licenses/LICENSE
krishnautoml-1.0.8.dist-info/METADATA
krishnautoml-1.0.8.dist-info/WHEEL
krishnautoml-1.0.8.dist-info/entry_points.txt
krishnautoml-1.0.8.dist-info/top_level.txt
krishnautoml-1.0.8.dist-info/RECORD
