Metadata-Version: 2.4
Name: krishnautoml
Version: 1.0.8
Summary: Beginner-friendly AutoML library for tabular data
Author: Krish
Author-email: Krishna <krishnatyagi2526@gmail.com>
License: MIT License
Requires-Python: >=3.7
License-File: LICENSE
Requires-Dist: pandas
Requires-Dist: numpy
Requires-Dist: scikit-learn
Requires-Dist: matplotlib
Requires-Dist: seaborn
Requires-Dist: jinja2
Requires-Dist: joblib
Requires-Dist: optuna
Requires-Dist: optuna-integration[lightgbm]
Provides-Extra: xgboost
Requires-Dist: xgboost; extra == "xgboost"
Provides-Extra: lightgbm
Requires-Dist: lightgbm; extra == "lightgbm"
Provides-Extra: catboost
Requires-Dist: catboost; extra == "catboost"
Dynamic: author
Dynamic: license-file
Dynamic: requires-python
